cli/__init__.py
cli/main.py
cli/router_config.py
cli/subscription_reporter.py
cli/utils.py
craftacoder-0.2.0.dist-info/METADATA
craftacoder-0.2.0.dist-info/WHEEL
craftacoder-0.2.0.dist-info/entry_points.txt
craftacoder-0.2.0.dist-info/top_level.txt
craftacoder-0.2.0.dist-info/RECORD
